spssdecode/__init__.py
spssdecode/ai_model.py
spssdecode/decoder.py
tests/__init__.py
tests/test_decoder.py
spssdecode-0.1.0.dist-info/LICENSE
spssdecode-0.1.0.dist-info/METADATA
spssdecode-0.1.0.dist-info/WHEEL
spssdecode-0.1.0.dist-info/top_level.txt
spssdecode-0.1.0.dist-info/RECORD
