Metadata-Version: 2.2
Name: spssdecode
Version: 0.1.0
Summary: A library to decode star maps into structured data.
Home-page: https://github.com/yourusername/spssdecode
Author: Sumedh Patil
Author-email: admin@aipresso.uk
Classifier: Programming Language :: Python :: 3
Classifier: License :: OSI Approved :: MIT License
Classifier: Operating System :: OS Independent
Requires-Python: >=3.7
License-File: LICENSE
Requires-Dist: numpy
Dynamic: author
Dynamic: author-email
Dynamic: classifier
Dynamic: description
Dynamic: description-content-type
Dynamic: home-page
Dynamic: requires-dist
Dynamic: requires-python
Dynamic: summary
